mathematics/__init__.py
mathematics/advance_math.py
mathematics/basic_math.py
veercal/__init__.py
veercal/calculator.py
veercal-0.1.0.dist-info/METADATA
veercal-0.1.0.dist-info/WHEEL
veercal-0.1.0.dist-info/entry_points.txt
veercal-0.1.0.dist-info/top_level.txt
veercal-0.1.0.dist-info/RECORD
